Metadata-Version: 2.4
Name: Misago
Version: 0.39.4
Summary: Misago is modern, fully featured forum application written in Python and ES6, powered by Django and React.js. It works out of the box and can be run alone or be connected to existing site with built in OAuth 2 client.
Home-page: http://www.misago-project.org/
Author: Rafał Pitoń
Author-email: kontakt@rpiton.com
License: GPLv2
Classifier: Development Status :: 4 - Beta
Classifier: Environment :: Web Environment
Classifier: Framework :: Django
Classifier: Intended Audience :: Developers
Classifier: Intended Audience :: System Administrators
Classifier: License :: OSI Approved :: GNU General Public License v2 (GPLv2)
Classifier: Operating System :: OS Independent
Classifier: Programming Language :: Python
Classifier: Programming Language :: Python :: 3.12
Classifier: Topic :: Internet :: WWW/HTTP
Classifier: Topic :: Internet :: WWW/HTTP :: Dynamic Content
Classifier: Topic :: Internet :: WWW/HTTP :: WSGI
Classifier: Topic :: Software Development :: Libraries :: Application Frameworks
Classifier: Topic :: Software Development :: Libraries :: Python Modules
License-File: LICENSE.rst
Requires-Dist: aiohttp==3.9.1
Requires-Dist: aiosignal==1.3.1
Requires-Dist: amqp==5.2.0
Requires-Dist: anyio==4.2.0
Requires-Dist: ariadne==0.21
Requires-Dist: ariadne-django==0.3.0
Requires-Dist: asgiref==3.7.2
Requires-Dist: attrs==23.1.0
Requires-Dist: billiard==4.2.0
Requires-Dist: black==23.12.0
Requires-Dist: celery[redis]==5.3.6
Requires-Dist: certifi==2023.11.17
Requires-Dist: cffi==1.16.0
Requires-Dist: charset-normalizer==3.3.2
Requires-Dist: click==8.1.7
Requires-Dist: click-didyoumean==0.3.0
Requires-Dist: click-plugins==1.1.1
Requires-Dist: click-repl==0.3.0
Requires-Dist: coverage[toml]==6.5.0
Requires-Dist: coveralls==3.3.1
Requires-Dist: cryptography==41.0.7
Requires-Dist: defusedxml==0.8.0rc2
Requires-Dist: django==4.2.8
Requires-Dist: django-debug-toolbar==4.2.0
Requires-Dist: django-js-asset==2.2.0
Requires-Dist: django-mptt==0.15.0
Requires-Dist: django-simple-sso==1.2.0
Requires-Dist: djangorestframework==3.14.0
Requires-Dist: docopt==0.6.2
Requires-Dist: faker==21.0.0
Requires-Dist: frozenlist==1.4.1
Requires-Dist: graphql-core==3.2.3
Requires-Dist: html5lib==1.1
Requires-Dist: idna==3.6
Requires-Dist: iniconfig==2.0.0
Requires-Dist: itsdangerous==0.24
Requires-Dist: kombu==5.3.4
Requires-Dist: markdown==3.5.1
Requires-Dist: multidict==6.0.4
Requires-Dist: mypy-extensions==1.0.0
Requires-Dist: oauthlib==3.2.2
Requires-Dist: packaging==23.2
Requires-Dist: pathspec==0.12.1
Requires-Dist: pillow==10.1.0
Requires-Dist: platformdirs==4.1.0
Requires-Dist: pluggy==1.3.0
Requires-Dist: prompt-toolkit==3.0.43
Requires-Dist: psycopg[binary]==3.1.16
Requires-Dist: psycopg-binary==3.1.16
Requires-Dist: pycparser==2.21
Requires-Dist: pyjwt==2.8.0
Requires-Dist: pytest==7.4.3
Requires-Dist: pytest-cov==4.1.0
Requires-Dist: pytest-django==4.7.0
Requires-Dist: pytest-mock==3.12.0
Requires-Dist: python-dateutil==2.8.2
Requires-Dist: python3-openid==3.2.0
Requires-Dist: pytz==2023.3.post1
Requires-Dist: pyyaml==6.0.1
Requires-Dist: redis==5.0.1
Requires-Dist: requests==2.31.0
Requires-Dist: requests-oauthlib==1.3.1
Requires-Dist: responses==0.24.1
Requires-Dist: ruff==0.1.8
Requires-Dist: six==1.16.0
Requires-Dist: sniffio==1.3.0
Requires-Dist: social-auth-app-django==5.4.0
Requires-Dist: social-auth-core==4.5.1
Requires-Dist: sqlparse==0.4.4
Requires-Dist: starlette==0.34.0
Requires-Dist: syrupy==4.6.0
Requires-Dist: typing-extensions==4.9.0
Requires-Dist: tzdata==2023.3
Requires-Dist: unidecode==1.3.7
Requires-Dist: urllib3==2.1.0
Requires-Dist: vine==5.1.0
Requires-Dist: wcwidth==0.2.12
Requires-Dist: webencodings==0.5.1
Requires-Dist: webservices[django]==0.7
Requires-Dist: yarl==1.9.4
Dynamic: author
Dynamic: author-email
Dynamic: classifier
Dynamic: description
Dynamic: description-content-type
Dynamic: home-page
Dynamic: license
Dynamic: license-file
Dynamic: requires-dist
Dynamic: summary
